lol_sync
