Metadata-Version: 1.1
Name: lolsync
Version: 0.21
Summary: Keep in sync with friends on League of Legends!
Home-page: https://github.com/jason2249/LoLSync
Author: Jason Lin
Author-email: jason_lin2@yahoo.com
License: MIT
Download-URL: https://github.com/jason2249/lolsync/tarball/0.21
Keywords: League of Legends,Friend,Sync
Platform: UNKNOWN
Classifier: Operating System :: MacOS
Classifier: Development Status :: 3 - Alpha
Classifier: License :: OSI Approved :: MIT License
Classifier: Programming Language :: Python :: 3.4
